pylib_essentials/__init__.py
pylib_essentials/schism_file.py
pylib_essentials/utility_functions.py
pylib_essentials-0.0.6.dist-info/METADATA
pylib_essentials-0.0.6.dist-info/WHEEL
pylib_essentials-0.0.6.dist-info/top_level.txt
pylib_essentials-0.0.6.dist-info/RECORD
